{"packages_components_intro.md":"47d21609","packages_request_intro.md":"9ebbb75e","packages_hooks_intro.md":"3e55eb49","packages_locale_intro.md":"6d526fbf","packages_constants_intro.md":"d87297c7","packages_vbencomponent_intro.md":"6fde2414","index.md":"72cd0bc4","other_faq.md":"38133c11","packages_styles_intro.md":"8519189a","packages_utils_intro.md":"db069f89","guide_uplog.md":"145df7d3","other_donate.md":"837df6e4","packages_vbencomponent_fetch.md":"29546a5e","packages_layouts_intro.md":"f905f568","packages_types_intro.md":"f15141db","other_follow.md":"9ec24fbc","guide_directory.md":"b9249330","guide_config.md":"5554b987","guide_quick-understanding.md":"49d03c9d","packages_demo_intro.md":"2a634c1d","guide_router.md":"b6fdf1a8","guide_deploy.md":"573a0312","guide_introduction.md":"0fd60273"}
